{
    "AIF": {
        "nodes": [
            {
                "nodeID": "12_168443705311874215",
                "text": "Donna knows some kind of secret",
                "type": "I"
            },
            {
                "nodeID": "13_168443705311874215",
                "text": "Female 1: it sounds like she knows some kind of secret",
                "type": "L"
            },
            {
                "nodeID": "14_168443705311874215",
                "text": "Analysing",
                "type": "YA"
            },
            {
                "nodeID": "15_168443705311874215",
                "text": "Lara: Female 1: it sounds like she knows some kind of secret",
                "type": "L"
            },
            {
                "nodeID": "16_168443705311874215",
                "text": "Hypothesising",
                "type": "YA"
            },
            {
                "nodeID": "18_168443705311874215",
                "text": "Female 2: Yeah",
                "type": "L"
            },
            {
                "nodeID": "19_168443705311874215",
                "text": "Analysing",
                "type": "YA"
            },
            {
                "nodeID": "20_168443705311874215",
                "text": "Lara: Female 2: Yeah",
                "type": "L"
            },
            {
                "nodeID": "22_168443705311874215",
                "text": "Default Transition",
                "type": "TA"
            },
            {
                "nodeID": "23_168443705311874215",
                "text": "Agreeing",
                "type": "YA"
            },
            {
                "nodeID": "30_168443705311874215",
                "text": "Donna and Nick Webster talked",
                "type": "I"
            },
            {
                "nodeID": "31_168443705311874215",
                "text": "Male 1: they talked",
                "type": "L"
            },
            {
                "nodeID": "32_168443705311874215",
                "text": "Analysing",
                "type": "YA"
            },
            {
                "nodeID": "33_168443705311874215",
                "text": "Lara: Male 1: they talked",
                "type": "L"
            },
            {
                "nodeID": "34_168443705311874215",
                "text": "Hypothesising",
                "type": "YA"
            },
            {
                "nodeID": "35_168443705311874215",
                "text": "there was time",
                "type": "I"
            },
            {
                "nodeID": "36_168443705311874215",
                "text": "Male 1: there was time",
                "type": "L"
            },
            {
                "nodeID": "37_168443705311874215",
                "text": "Analysing",
                "type": "YA"
            },
            {
                "nodeID": "38_168443705311874215",
                "text": "Lara: Male 1: there was time",
                "type": "L"
            },
            {
                "nodeID": "39_168443705311874215",
                "text": "Hypothesising",
                "type": "YA"
            },
            {
                "nodeID": "41_168443705311874215",
                "text": "Donna and Nick Webster met in the bar",
                "type": "I"
            },
            {
                "nodeID": "42_168443705311874215",
                "text": "Male 1: they met in the bar",
                "type": "L"
            },
            {
                "nodeID": "43_168443705311874215",
                "text": "Analysing",
                "type": "YA"
            },
            {
                "nodeID": "44_168443705311874215",
                "text": "Lara: Male 1: they met in the bar",
                "type": "L"
            },
            {
                "nodeID": "45_168443705311874215",
                "text": "Hypothesising",
                "type": "YA"
            },
            {
                "nodeID": "46_168443705311874215",
                "text": "Default Transition",
                "type": "TA"
            },
            {
                "nodeID": "47_168443705311874215",
                "text": "Default Transition",
                "type": "TA"
            },
            {
                "nodeID": "48_168443705311874215",
                "text": "Donna and Nick Webster talked about the land on Devil's Well",
                "type": "I"
            },
            {
                "nodeID": "49_168443705311874215",
                "text": "Male 1: they talked about that",
                "type": "L"
            },
            {
                "nodeID": "50_168443705311874215",
                "text": "Analysing",
                "type": "YA"
            },
            {
                "nodeID": "51_168443705311874215",
                "text": "Lara: Male 1: they talked about that",
                "type": "L"
            },
            {
                "nodeID": "52_168443705311874215",
                "text": "Hypothesising",
                "type": "YA"
            },
            {
                "nodeID": "53_168443705311874215",
                "text": "Default Transition",
                "type": "TA"
            },
            {
                "nodeID": "54_168443705311874215",
                "text": "Default Rephrase",
                "type": "MA"
            },
            {
                "nodeID": "55_168443705311874215",
                "text": "Restating",
                "type": "YA"
            },
            {
                "nodeID": "57_168443705311874215",
                "text": "Female 2: No",
                "type": "L"
            },
            {
                "nodeID": "58_168443705311874215",
                "text": "Analysing",
                "type": "YA"
            },
            {
                "nodeID": "59_168443705311874215",
                "text": "Lara: Female 2: No",
                "type": "L"
            },
            {
                "nodeID": "61_168443705311874215",
                "text": "Default Transition",
                "type": "TA"
            },
            {
                "nodeID": "62_168443705311874215",
                "text": "Disagreeing",
                "type": "YA"
            },
            {
                "nodeID": "63_168443705311874215",
                "text": "Donna left the note on her menu",
                "type": "I"
            },
            {
                "nodeID": "64_168443705311874215",
                "text": "Female 2: she left the note",
                "type": "L"
            },
            {
                "nodeID": "65_168443705311874215",
                "text": "Analysing",
                "type": "YA"
            },
            {
                "nodeID": "66_168443705311874215",
                "text": "Lara: Female 2: she left the note",
                "type": "L"
            },
            {
                "nodeID": "67_168443705311874215",
                "text": "Hypothesising",
                "type": "YA"
            },
            {
                "nodeID": "68_168443705311874215",
                "text": "Default Transition",
                "type": "TA"
            },
            {
                "nodeID": "69_168443705311874215",
                "text": "Default Conflict",
                "type": "CA"
            },
            {
                "nodeID": "70_168443705311874215",
                "text": "Alternative Giving",
                "type": "YA"
            },
            {
                "nodeID": "72_168443705311874215",
                "text": "Female 2:  she left a note on her menu",
                "type": "L"
            },
            {
                "nodeID": "73_168443705311874215",
                "text": "Analysing",
                "type": "YA"
            },
            {
                "nodeID": "74_168443705311874215",
                "text": "Lara: Female 2:  she left a note on her menu",
                "type": "L"
            },
            {
                "nodeID": "76_168443705311874215",
                "text": "Default Transition",
                "type": "TA"
            },
            {
                "nodeID": "77_168443705311874215",
                "text": "Asserting",
                "type": "YA"
            },
            {
                "nodeID": "78_168443705311874215",
                "text": "Donna left the matchbox on the counter for Nick Webster",
                "type": "I"
            },
            {
                "nodeID": "79_168443705311874215",
                "text": "Female 2: the matchbox on the counter for Nick",
                "type": "L"
            },
            {
                "nodeID": "80_168443705311874215",
                "text": "Analysing",
                "type": "YA"
            },
            {
                "nodeID": "81_168443705311874215",
                "text": "Lara: Female 2: the matchbox on the counter for Nick",
                "type": "L"
            },
            {
                "nodeID": "82_168443705311874215",
                "text": "Asserting",
                "type": "YA"
            },
            {
                "nodeID": "83_168443705311874215",
                "text": "Default Transition",
                "type": "TA"
            },
            {
                "nodeID": "84_168443705311874215",
                "text": "Nick Webster never got the chance to see the note and the matchbox",
                "type": "I"
            },
            {
                "nodeID": "85_168443705311874215",
                "text": "Female 2:  he never got the chance to see it",
                "type": "L"
            },
            {
                "nodeID": "86_168443705311874215",
                "text": "Analysing",
                "type": "YA"
            },
            {
                "nodeID": "87_168443705311874215",
                "text": "Lara: Female 2:  he never got the chance to see it",
                "type": "L"
            },
            {
                "nodeID": "88_168443705311874215",
                "text": "Asserting",
                "type": "YA"
            },
            {
                "nodeID": "89_168443705311874215",
                "text": "Default Transition",
                "type": "TA"
            },
            {
                "nodeID": "90_168443705311874215",
                "text": "Default Conflict",
                "type": "CA"
            },
            {
                "nodeID": "91_168443705311874215",
                "text": "Disagreeing",
                "type": "YA"
            },
            {
                "nodeID": "92_168443705311874215",
                "text": "Nick Webster does or does not say that, he knows who's behind the threats, and everything",
                "type": "I"
            },
            {
                "nodeID": "93_168443705311874215",
                "text": "Male 1: he says that, he knows who's behind the threats, and everything",
                "type": "L"
            },
            {
                "nodeID": "94_168443705311874215",
                "text": "Analysing",
                "type": "YA"
            },
            {
                "nodeID": "95_168443705311874215",
                "text": "Lara: Male 1: he says that, he knows who's behind the threats, and everything",
                "type": "L"
            },
            {
                "nodeID": "96_168443705311874215",
                "text": "Pure Questioning",
                "type": "YA"
            },
            {
                "nodeID": "98_168443705311874215",
                "text": "Female 2: Yeah",
                "type": "L"
            },
            {
                "nodeID": "99_168443705311874215",
                "text": "Analysing",
                "type": "YA"
            },
            {
                "nodeID": "100_168443705311874215",
                "text": "Lara: Female 2: Yeah",
                "type": "L"
            },
            {
                "nodeID": "102_168443705311874215",
                "text": "Default Transition",
                "type": "TA"
            },
            {
                "nodeID": "103_168443705311874215",
                "text": "Agreeing",
                "type": "YA"
            },
            {
                "nodeID": "104_168443705311874215",
                "text": "maybe multiple people were threatening Nick Webster",
                "type": "I"
            },
            {
                "nodeID": "105_168443705311874215",
                "text": "Female 1: maybe multiple people were threatening him",
                "type": "L"
            },
            {
                "nodeID": "106_168443705311874215",
                "text": "Analysing",
                "type": "YA"
            },
            {
                "nodeID": "107_168443705311874215",
                "text": "Lara: Female 1: maybe multiple people were threatening him",
                "type": "L"
            },
            {
                "nodeID": "108_168443705311874215",
                "text": "Assertive Questioning",
                "type": "YA"
            },
            {
                "nodeID": "112_168443705311874215",
                "text": "Donna knows about a different person threatening Nick Webster",
                "type": "I"
            },
            {
                "nodeID": "113_168443705311874215",
                "text": "Female 1:  she knows about a different one",
                "type": "L"
            },
            {
                "nodeID": "114_168443705311874215",
                "text": "Analysing",
                "type": "YA"
            },
            {
                "nodeID": "115_168443705311874215",
                "text": "Lara: Female 1:  she knows about a different one",
                "type": "L"
            },
            {
                "nodeID": "116_168443705311874215",
                "text": "Assertive Questioning",
                "type": "YA"
            },
            {
                "nodeID": "119_168443705311874215",
                "text": "Default Inference",
                "type": "RA"
            },
            {
                "nodeID": "121_168443705311874215",
                "text": "Default Transition",
                "type": "TA"
            },
            {
                "nodeID": "123_168443705311874215",
                "text": "Arguing",
                "type": "YA"
            },
            {
                "nodeID": "125_168443705311874215",
                "text": "Female 2: Yeah",
                "type": "L"
            },
            {
                "nodeID": "126_168443705311874215",
                "text": "Analysing",
                "type": "YA"
            },
            {
                "nodeID": "127_168443705311874215",
                "text": "Lara: Female 2: Yeah",
                "type": "L"
            },
            {
                "nodeID": "129_168443705311874215",
                "text": "Default Transition",
                "type": "TA"
            },
            {
                "nodeID": "130_168443705311874215",
                "text": "Agreeing",
                "type": "YA"
            },
            {
                "nodeID": "131_168443705311874215",
                "text": "Default Inference",
                "type": "RA"
            },
            {
                "nodeID": "132_168443705311874215",
                "text": "Arguing",
                "type": "YA"
            }
        ],
        "edges": [
            {
                "edgeID": 1,
                "fromID": "14_168443705311874215",
                "toID": "13_168443705311874215"
            },
            {
                "edgeID": 2,
                "fromID": "15_168443705311874215",
                "toID": "14_168443705311874215"
            },
            {
                "edgeID": 3,
                "fromID": "13_168443705311874215",
                "toID": "16_168443705311874215"
            },
            {
                "edgeID": 4,
                "fromID": "16_168443705311874215",
                "toID": "12_168443705311874215"
            },
            {
                "edgeID": 5,
                "fromID": "19_168443705311874215",
                "toID": "18_168443705311874215"
            },
            {
                "edgeID": 6,
                "fromID": "20_168443705311874215",
                "toID": "19_168443705311874215"
            },
            {
                "edgeID": 7,
                "fromID": "13_168443705311874215",
                "toID": "22_168443705311874215"
            },
            {
                "edgeID": 8,
                "fromID": "22_168443705311874215",
                "toID": "18_168443705311874215"
            },
            {
                "edgeID": 9,
                "fromID": "22_168443705311874215",
                "toID": "23_168443705311874215"
            },
            {
                "edgeID": 10,
                "fromID": "23_168443705311874215",
                "toID": "12_168443705311874215"
            },
            {
                "edgeID": 11,
                "fromID": "32_168443705311874215",
                "toID": "31_168443705311874215"
            },
            {
                "edgeID": 12,
                "fromID": "33_168443705311874215",
                "toID": "32_168443705311874215"
            },
            {
                "edgeID": 13,
                "fromID": "31_168443705311874215",
                "toID": "34_168443705311874215"
            },
            {
                "edgeID": 14,
                "fromID": "34_168443705311874215",
                "toID": "30_168443705311874215"
            },
            {
                "edgeID": 15,
                "fromID": "37_168443705311874215",
                "toID": "36_168443705311874215"
            },
            {
                "edgeID": 16,
                "fromID": "38_168443705311874215",
                "toID": "37_168443705311874215"
            },
            {
                "edgeID": 17,
                "fromID": "36_168443705311874215",
                "toID": "39_168443705311874215"
            },
            {
                "edgeID": 18,
                "fromID": "39_168443705311874215",
                "toID": "35_168443705311874215"
            },
            {
                "edgeID": 19,
                "fromID": "43_168443705311874215",
                "toID": "42_168443705311874215"
            },
            {
                "edgeID": 20,
                "fromID": "44_168443705311874215",
                "toID": "43_168443705311874215"
            },
            {
                "edgeID": 21,
                "fromID": "42_168443705311874215",
                "toID": "45_168443705311874215"
            },
            {
                "edgeID": 22,
                "fromID": "45_168443705311874215",
                "toID": "41_168443705311874215"
            },
            {
                "edgeID": 23,
                "fromID": "31_168443705311874215",
                "toID": "46_168443705311874215"
            },
            {
                "edgeID": 24,
                "fromID": "46_168443705311874215",
                "toID": "36_168443705311874215"
            },
            {
                "edgeID": 25,
                "fromID": "36_168443705311874215",
                "toID": "47_168443705311874215"
            },
            {
                "edgeID": 26,
                "fromID": "47_168443705311874215",
                "toID": "42_168443705311874215"
            },
            {
                "edgeID": 27,
                "fromID": "50_168443705311874215",
                "toID": "49_168443705311874215"
            },
            {
                "edgeID": 28,
                "fromID": "51_168443705311874215",
                "toID": "50_168443705311874215"
            },
            {
                "edgeID": 29,
                "fromID": "49_168443705311874215",
                "toID": "52_168443705311874215"
            },
            {
                "edgeID": 30,
                "fromID": "52_168443705311874215",
                "toID": "48_168443705311874215"
            },
            {
                "edgeID": 31,
                "fromID": "31_168443705311874215",
                "toID": "53_168443705311874215"
            },
            {
                "edgeID": 32,
                "fromID": "53_168443705311874215",
                "toID": "49_168443705311874215"
            },
            {
                "edgeID": 33,
                "fromID": "48_168443705311874215",
                "toID": "54_168443705311874215"
            },
            {
                "edgeID": 34,
                "fromID": "54_168443705311874215",
                "toID": "30_168443705311874215"
            },
            {
                "edgeID": 35,
                "fromID": "53_168443705311874215",
                "toID": "55_168443705311874215"
            },
            {
                "edgeID": 36,
                "fromID": "55_168443705311874215",
                "toID": "54_168443705311874215"
            },
            {
                "edgeID": 37,
                "fromID": "58_168443705311874215",
                "toID": "57_168443705311874215"
            },
            {
                "edgeID": 38,
                "fromID": "59_168443705311874215",
                "toID": "58_168443705311874215"
            },
            {
                "edgeID": 39,
                "fromID": "49_168443705311874215",
                "toID": "61_168443705311874215"
            },
            {
                "edgeID": 40,
                "fromID": "61_168443705311874215",
                "toID": "57_168443705311874215"
            },
            {
                "edgeID": 41,
                "fromID": "61_168443705311874215",
                "toID": "62_168443705311874215"
            },
            {
                "edgeID": 42,
                "fromID": "62_168443705311874215",
                "toID": "48_168443705311874215"
            },
            {
                "edgeID": 43,
                "fromID": "65_168443705311874215",
                "toID": "64_168443705311874215"
            },
            {
                "edgeID": 44,
                "fromID": "66_168443705311874215",
                "toID": "65_168443705311874215"
            },
            {
                "edgeID": 45,
                "fromID": "64_168443705311874215",
                "toID": "67_168443705311874215"
            },
            {
                "edgeID": 46,
                "fromID": "67_168443705311874215",
                "toID": "63_168443705311874215"
            },
            {
                "edgeID": 47,
                "fromID": "49_168443705311874215",
                "toID": "68_168443705311874215"
            },
            {
                "edgeID": 48,
                "fromID": "68_168443705311874215",
                "toID": "64_168443705311874215"
            },
            {
                "edgeID": 49,
                "fromID": "63_168443705311874215",
                "toID": "69_168443705311874215"
            },
            {
                "edgeID": 50,
                "fromID": "69_168443705311874215",
                "toID": "48_168443705311874215"
            },
            {
                "edgeID": 51,
                "fromID": "68_168443705311874215",
                "toID": "70_168443705311874215"
            },
            {
                "edgeID": 52,
                "fromID": "70_168443705311874215",
                "toID": "69_168443705311874215"
            },
            {
                "edgeID": 53,
                "fromID": "73_168443705311874215",
                "toID": "72_168443705311874215"
            },
            {
                "edgeID": 54,
                "fromID": "74_168443705311874215",
                "toID": "73_168443705311874215"
            },
            {
                "edgeID": 55,
                "fromID": "64_168443705311874215",
                "toID": "76_168443705311874215"
            },
            {
                "edgeID": 56,
                "fromID": "76_168443705311874215",
                "toID": "72_168443705311874215"
            },
            {
                "edgeID": 57,
                "fromID": "72_168443705311874215",
                "toID": "77_168443705311874215"
            },
            {
                "edgeID": 58,
                "fromID": "77_168443705311874215",
                "toID": "63_168443705311874215"
            },
            {
                "edgeID": 59,
                "fromID": "80_168443705311874215",
                "toID": "79_168443705311874215"
            },
            {
                "edgeID": 60,
                "fromID": "81_168443705311874215",
                "toID": "80_168443705311874215"
            },
            {
                "edgeID": 61,
                "fromID": "79_168443705311874215",
                "toID": "82_168443705311874215"
            },
            {
                "edgeID": 62,
                "fromID": "82_168443705311874215",
                "toID": "78_168443705311874215"
            },
            {
                "edgeID": 63,
                "fromID": "72_168443705311874215",
                "toID": "83_168443705311874215"
            },
            {
                "edgeID": 64,
                "fromID": "83_168443705311874215",
                "toID": "79_168443705311874215"
            },
            {
                "edgeID": 65,
                "fromID": "86_168443705311874215",
                "toID": "85_168443705311874215"
            },
            {
                "edgeID": 66,
                "fromID": "87_168443705311874215",
                "toID": "86_168443705311874215"
            },
            {
                "edgeID": 67,
                "fromID": "85_168443705311874215",
                "toID": "88_168443705311874215"
            },
            {
                "edgeID": 68,
                "fromID": "88_168443705311874215",
                "toID": "84_168443705311874215"
            },
            {
                "edgeID": 69,
                "fromID": "79_168443705311874215",
                "toID": "89_168443705311874215"
            },
            {
                "edgeID": 70,
                "fromID": "89_168443705311874215",
                "toID": "85_168443705311874215"
            },
            {
                "edgeID": 71,
                "fromID": "84_168443705311874215",
                "toID": "90_168443705311874215"
            },
            {
                "edgeID": 72,
                "fromID": "90_168443705311874215",
                "toID": "78_168443705311874215"
            },
            {
                "edgeID": 73,
                "fromID": "89_168443705311874215",
                "toID": "91_168443705311874215"
            },
            {
                "edgeID": 74,
                "fromID": "91_168443705311874215",
                "toID": "90_168443705311874215"
            },
            {
                "edgeID": 75,
                "fromID": "94_168443705311874215",
                "toID": "93_168443705311874215"
            },
            {
                "edgeID": 76,
                "fromID": "95_168443705311874215",
                "toID": "94_168443705311874215"
            },
            {
                "edgeID": 77,
                "fromID": "93_168443705311874215",
                "toID": "96_168443705311874215"
            },
            {
                "edgeID": 78,
                "fromID": "96_168443705311874215",
                "toID": "92_168443705311874215"
            },
            {
                "edgeID": 79,
                "fromID": "99_168443705311874215",
                "toID": "98_168443705311874215"
            },
            {
                "edgeID": 80,
                "fromID": "100_168443705311874215",
                "toID": "99_168443705311874215"
            },
            {
                "edgeID": 81,
                "fromID": "93_168443705311874215",
                "toID": "102_168443705311874215"
            },
            {
                "edgeID": 82,
                "fromID": "102_168443705311874215",
                "toID": "98_168443705311874215"
            },
            {
                "edgeID": 83,
                "fromID": "102_168443705311874215",
                "toID": "103_168443705311874215"
            },
            {
                "edgeID": 84,
                "fromID": "103_168443705311874215",
                "toID": "92_168443705311874215"
            },
            {
                "edgeID": 85,
                "fromID": "106_168443705311874215",
                "toID": "105_168443705311874215"
            },
            {
                "edgeID": 86,
                "fromID": "107_168443705311874215",
                "toID": "106_168443705311874215"
            },
            {
                "edgeID": 87,
                "fromID": "105_168443705311874215",
                "toID": "108_168443705311874215"
            },
            {
                "edgeID": 88,
                "fromID": "108_168443705311874215",
                "toID": "104_168443705311874215"
            },
            {
                "edgeID": 89,
                "fromID": "114_168443705311874215",
                "toID": "113_168443705311874215"
            },
            {
                "edgeID": 90,
                "fromID": "115_168443705311874215",
                "toID": "114_168443705311874215"
            },
            {
                "edgeID": 91,
                "fromID": "113_168443705311874215",
                "toID": "116_168443705311874215"
            },
            {
                "edgeID": 92,
                "fromID": "116_168443705311874215",
                "toID": "112_168443705311874215"
            },
            {
                "edgeID": 93,
                "fromID": "92_168443705311874215",
                "toID": "119_168443705311874215"
            },
            {
                "edgeID": 94,
                "fromID": "119_168443705311874215",
                "toID": "112_168443705311874215"
            },
            {
                "edgeID": 95,
                "fromID": "104_168443705311874215",
                "toID": "119_168443705311874215"
            },
            {
                "edgeID": 96,
                "fromID": "105_168443705311874215",
                "toID": "121_168443705311874215"
            },
            {
                "edgeID": 97,
                "fromID": "121_168443705311874215",
                "toID": "113_168443705311874215"
            },
            {
                "edgeID": 98,
                "fromID": "93_168443705311874215",
                "toID": "121_168443705311874215"
            },
            {
                "edgeID": 99,
                "fromID": "121_168443705311874215",
                "toID": "123_168443705311874215"
            },
            {
                "edgeID": 100,
                "fromID": "123_168443705311874215",
                "toID": "119_168443705311874215"
            },
            {
                "edgeID": 101,
                "fromID": "126_168443705311874215",
                "toID": "125_168443705311874215"
            },
            {
                "edgeID": 102,
                "fromID": "127_168443705311874215",
                "toID": "126_168443705311874215"
            },
            {
                "edgeID": 103,
                "fromID": "113_168443705311874215",
                "toID": "129_168443705311874215"
            },
            {
                "edgeID": 104,
                "fromID": "129_168443705311874215",
                "toID": "125_168443705311874215"
            },
            {
                "edgeID": 105,
                "fromID": "129_168443705311874215",
                "toID": "130_168443705311874215"
            },
            {
                "edgeID": 106,
                "fromID": "130_168443705311874215",
                "toID": "112_168443705311874215"
            },
            {
                "edgeID": 107,
                "fromID": "35_168443705311874215",
                "toID": "131_168443705311874215"
            },
            {
                "edgeID": 108,
                "fromID": "131_168443705311874215",
                "toID": "30_168443705311874215"
            },
            {
                "edgeID": 109,
                "fromID": "46_168443705311874215",
                "toID": "132_168443705311874215"
            },
            {
                "edgeID": 110,
                "fromID": "132_168443705311874215",
                "toID": "131_168443705311874215"
            }
        ],
        "schemefulfillments": [
            {
                "nodeID": "14_168443705311874215",
                "schemeID": "75"
            },
            {
                "nodeID": "16_168443705311874215",
                "schemeID": "410"
            },
            {
                "nodeID": "19_168443705311874215",
                "schemeID": "75"
            },
            {
                "nodeID": "22_168443705311874215",
                "schemeID": "82"
            },
            {
                "nodeID": "23_168443705311874215",
                "schemeID": "77"
            },
            {
                "nodeID": "32_168443705311874215",
                "schemeID": "75"
            },
            {
                "nodeID": "34_168443705311874215",
                "schemeID": "410"
            },
            {
                "nodeID": "37_168443705311874215",
                "schemeID": "75"
            },
            {
                "nodeID": "39_168443705311874215",
                "schemeID": "410"
            },
            {
                "nodeID": "43_168443705311874215",
                "schemeID": "75"
            },
            {
                "nodeID": "45_168443705311874215",
                "schemeID": "410"
            },
            {
                "nodeID": "46_168443705311874215",
                "schemeID": "82"
            },
            {
                "nodeID": "47_168443705311874215",
                "schemeID": "82"
            },
            {
                "nodeID": "50_168443705311874215",
                "schemeID": "75"
            },
            {
                "nodeID": "52_168443705311874215",
                "schemeID": "410"
            },
            {
                "nodeID": "53_168443705311874215",
                "schemeID": "82"
            },
            {
                "nodeID": "54_168443705311874215",
                "schemeID": "144"
            },
            {
                "nodeID": "55_168443705311874215",
                "schemeID": "101"
            },
            {
                "nodeID": "58_168443705311874215",
                "schemeID": "75"
            },
            {
                "nodeID": "61_168443705311874215",
                "schemeID": "82"
            },
            {
                "nodeID": "62_168443705311874215",
                "schemeID": "78"
            },
            {
                "nodeID": "65_168443705311874215",
                "schemeID": "75"
            },
            {
                "nodeID": "67_168443705311874215",
                "schemeID": "410"
            },
            {
                "nodeID": "68_168443705311874215",
                "schemeID": "82"
            },
            {
                "nodeID": "69_168443705311874215",
                "schemeID": "71"
            },
            {
                "nodeID": "70_168443705311874215",
                "schemeID": "483"
            },
            {
                "nodeID": "73_168443705311874215",
                "schemeID": "75"
            },
            {
                "nodeID": "76_168443705311874215",
                "schemeID": "82"
            },
            {
                "nodeID": "77_168443705311874215",
                "schemeID": "74"
            },
            {
                "nodeID": "80_168443705311874215",
                "schemeID": "75"
            },
            {
                "nodeID": "82_168443705311874215",
                "schemeID": "74"
            },
            {
                "nodeID": "83_168443705311874215",
                "schemeID": "82"
            },
            {
                "nodeID": "86_168443705311874215",
                "schemeID": "75"
            },
            {
                "nodeID": "88_168443705311874215",
                "schemeID": "74"
            },
            {
                "nodeID": "89_168443705311874215",
                "schemeID": "82"
            },
            {
                "nodeID": "90_168443705311874215",
                "schemeID": "71"
            },
            {
                "nodeID": "91_168443705311874215",
                "schemeID": "78"
            },
            {
                "nodeID": "94_168443705311874215",
                "schemeID": "75"
            },
            {
                "nodeID": "96_168443705311874215",
                "schemeID": "91"
            },
            {
                "nodeID": "99_168443705311874215",
                "schemeID": "75"
            },
            {
                "nodeID": "102_168443705311874215",
                "schemeID": "82"
            },
            {
                "nodeID": "103_168443705311874215",
                "schemeID": "77"
            },
            {
                "nodeID": "106_168443705311874215",
                "schemeID": "75"
            },
            {
                "nodeID": "108_168443705311874215",
                "schemeID": "73"
            },
            {
                "nodeID": "114_168443705311874215",
                "schemeID": "75"
            },
            {
                "nodeID": "116_168443705311874215",
                "schemeID": "73"
            },
            {
                "nodeID": "119_168443705311874215",
                "schemeID": "72"
            },
            {
                "nodeID": "121_168443705311874215",
                "schemeID": "82"
            },
            {
                "nodeID": "123_168443705311874215",
                "schemeID": "80"
            },
            {
                "nodeID": "126_168443705311874215",
                "schemeID": "75"
            },
            {
                "nodeID": "129_168443705311874215",
                "schemeID": "82"
            },
            {
                "nodeID": "130_168443705311874215",
                "schemeID": "77"
            },
            {
                "nodeID": "131_168443705311874215",
                "schemeID": "72"
            },
            {
                "nodeID": "132_168443705311874215",
                "schemeID": "80"
            }
        ],
        "participants": [
            {
                "participantID": 1,
                "firstname": "Participant",
                "surname": "Rachel"
            },
            {
                "participantID": 2,
                "firstname": "Participant",
                "surname": "Carolyn"
            },
            {
                "participantID": 3,
                "firstname": "Participant",
                "surname": "Mo"
            },
            {
                "participantID": 4,
                "firstname": "Participant",
                "surname": "Zoe"
            },
            {
                "participantID": 5,
                "firstname": "Participant",
                "surname": "Claire"
            },
            {
                "participantID": 6,
                "firstname": "Participant",
                "surname": "Lee"
            },
            {
                "participantID": 7,
                "firstname": "Participant",
                "surname": "Sally"
            },
            {
                "participantID": 8,
                "firstname": "Participant",
                "surname": "Kalbir"
            },
            {
                "participantID": 9,
                "firstname": "Participant",
                "surname": "Alice"
            },
            {
                "participantID": 10,
                "firstname": "Anne",
                "surname": "Robinson"
            },
            {
                "participantID": 11,
                "firstname": "Diane",
                "surname": "Munday"
            },
            {
                "participantID": 12,
                "firstname": "Neena",
                "surname": "Modi"
            },
            {
                "participantID": 13,
                "firstname": "David",
                "surname": "Steel"
            },
            {
                "participantID": 14,
                "firstname": "Neil",
                "surname": "Lyndon"
            },
            {
                "participantID": 15,
                "firstname": "Female",
                "surname": "1"
            },
            {
                "participantID": 16,
                "firstname": "Male",
                "surname": "1"
            },
            {
                "participantID": 17,
                "firstname": "Female",
                "surname": "2"
            },
            {
                "participantID": 18,
                "firstname": "the",
                "surname": "complainant"
            },
            {
                "participantID": 19,
                "firstname": "Cherie",
                "surname": ""
            },
            {
                "participantID": 20,
                "firstname": "woman",
                "surname": ""
            },
            {
                "participantID": 21,
                "firstname": "Woman",
                "surname": ""
            }
        ],
        "locutions": [
            {
                "nodeID": "13_168443705311874215",
                "personID": 15,
                "start": "2023-05-12 18:32:02",
                "end": null
            },
            {
                "nodeID": "18_168443705311874215",
                "personID": 17,
                "start": "2023-05-12 18:32:05",
                "end": null
            },
            {
                "nodeID": "31_168443705311874215",
                "personID": 16,
                "start": "2023-05-12 18:32:15",
                "end": null
            },
            {
                "nodeID": "36_168443705311874215",
                "personID": 16,
                "start": "2023-05-12 18:32:16",
                "end": null
            },
            {
                "nodeID": "42_168443705311874215",
                "personID": 16,
                "start": "2023-05-12 18:32:17",
                "end": null
            },
            {
                "nodeID": "49_168443705311874215",
                "personID": 16,
                "start": "2023-05-12 18:32:19",
                "end": null
            },
            {
                "nodeID": "57_168443705311874215",
                "personID": 17,
                "start": "2023-05-12 18:32:20",
                "end": null
            },
            {
                "nodeID": "64_168443705311874215",
                "personID": 17,
                "start": "2023-05-12 18:32:21",
                "end": null
            },
            {
                "nodeID": "72_168443705311874215",
                "personID": 17,
                "start": "2023-05-12 18:32:23",
                "end": null
            },
            {
                "nodeID": "79_168443705311874215",
                "personID": 17,
                "start": "2023-05-12 18:32:26",
                "end": null
            },
            {
                "nodeID": "85_168443705311874215",
                "personID": 17,
                "start": "2023-05-12 18:32:28",
                "end": null
            },
            {
                "nodeID": "93_168443705311874215",
                "personID": 16,
                "start": "2023-05-12 18:32:32",
                "end": null
            },
            {
                "nodeID": "98_168443705311874215",
                "personID": 17,
                "start": "2023-05-12 18:32:35",
                "end": null
            },
            {
                "nodeID": "105_168443705311874215",
                "personID": 15,
                "start": "2023-05-12 18:32:37",
                "end": null
            },
            {
                "nodeID": "113_168443705311874215",
                "personID": 15,
                "start": "2023-05-12 18:32:40",
                "end": null
            },
            {
                "nodeID": "125_168443705311874215",
                "personID": 17,
                "start": "2023-05-12 18:32:42",
                "end": null
            }
        ],
        "descriptorfulfillments": [],
        "cqdescriptorfulfillments": []
    },
    "text": "Part 8<br>F1 [2023/05/12 18:32:00 GMT+0000]:\tWell, <span id=\"node13_168443705311874215\" class=\"highlighted\">it sounds like she knows some kind of secret</span>.<br><br>F2:\t<span id=\"node18_168443705311874215\" class=\"highlighted\">Yeah</span>.<br><br>F1:\tSo, we need to talk about Devil's Well, about the land on Devil's Well, on Wednesday, at 11p.m.<br><br>F2:\tYeah.<br><br>M1:\tOkay.<br><br>F1:\tSo, maybe she was planning\u2026<br><br>M1:\tSo, <span id=\"node31_168443705311874215\" class=\"highlighted\">they talked</span>, <span id=\"node36_168443705311874215\" class=\"highlighted\">there was time</span>, <span id=\"node42_168443705311874215\" class=\"highlighted\">they met in the bar</span>, and <span id=\"node49_168443705311874215\" class=\"highlighted\">they talked about that</span>?<br><br>F2:\t<span id=\"node57_168443705311874215\" class=\"highlighted\">No</span>, <span id=\"node64_168443705311874215\" class=\"highlighted\">she left the note</span>, I think.&nbsp; Yeah, so,<span id=\"node72_168443705311874215\" class=\"highlighted\"> she left a note on her menu</span>, and <span id=\"node79_168443705311874215\" class=\"highlighted\">the matchbox on the counter for Nick</span>, but<span id=\"node85_168443705311874215\" class=\"highlighted\"> he never got the chance to see it</span>.<br><br>M1:\tOh, okay.&nbsp; But <span id=\"node93_168443705311874215\" class=\"highlighted\">he says that, he knows who's behind the threats, and everything</span>?<br><br>F2:\t<span id=\"node98_168443705311874215\" class=\"highlighted\">Yeah</span>.<br><br>M1:\tOkay.<br><br>F1:\tSo, <span id=\"node105_168443705311874215\" class=\"highlighted\">maybe multiple people were threatening him</span>, and<span id=\"node113_168443705311874215\" class=\"highlighted hlcurrent\"> she knows about a different one</span>?<br><br>F2:\t<span id=\"node125_168443705311874215\" class=\"highlighted\">Yeah</span>.<br><br>M1:\tWhere did you get the coding stuff?&nbsp; I remember there was a paper.<br><br>F2:\tYeah.<br><br>F1:\tOh, yeah, but I think it was basically just explaining that you moved the alphabet.<br><br>F2:\tBut should we just do it to see what it actually says, in case there's anything useful?<br><br>F1:\tYeah.<br><br>M1:\tYeah.<br><br>F2:\tIs this the threatening note, or\u2026?<br><br>F1:\tYeah, so that's the threatening note on the poster.<br><br>M1:\tYeah, I wrote it down, here.<br><br>F1:\tOh, good.<br><br>M1:\tBut the thing is that we don't know because\u2026okay.<br><br>F1:\tOkay, so we need something\u2026okay.&nbsp; Right, can I\u2026oh.<br><br>M1:\tYes, I was going to use it.<br><br>F1:\tOh, okay.&nbsp; Do we have another page?&nbsp; I can rip my page up, because I would also like to try it.<br><br>M1:\tDo you have one more paper?<br><br>F3 [00:01:25]:\tI can get some.<br>",
    "OVA": {
        "firstname": "Louise",
        "surname": "Whyman",
        "url": "",
        "nodes": [
            {
                "nodeID": "12_168443705311874215",
                "visible": true,
                "x": 320,
                "y": 62,
                "timestamp": ""
            },
            {
                "nodeID": "13_168443705311874215",
                "visible": true,
                "x": 774,
                "y": 60,
                "timestamp": "Fri May 12 2023 20:32:02 GMT+0200"
            },
            {
                "nodeID": "14_168443705311874215",
                "visible": false,
                "x": 0,
                "y": 0,
                "timestamp": ""
            },
            {
                "nodeID": "15_168443705311874215",
                "visible": false,
                "x": 0,
                "y": 0,
                "timestamp": ""
            },
            {
                "nodeID": "16_168443705311874215",
                "visible": true,
                "x": 554,
                "y": 63,
                "timestamp": ""
            },
            {
                "nodeID": "18_168443705311874215",
                "visible": true,
                "x": 766,
                "y": 192,
                "timestamp": "Fri May 12 2023 20:32:05 GMT+0200"
            },
            {
                "nodeID": "19_168443705311874215",
                "visible": false,
                "x": 0,
                "y": 0,
                "timestamp": ""
            },
            {
                "nodeID": "20_168443705311874215",
                "visible": false,
                "x": 0,
                "y": 0,
                "timestamp": ""
            },
            {
                "nodeID": "22_168443705311874215",
                "visible": true,
                "x": 770,
                "y": 140,
                "timestamp": ""
            },
            {
                "nodeID": "23_168443705311874215",
                "visible": true,
                "x": 545,
                "y": 115,
                "timestamp": ""
            },
            {
                "nodeID": "30_168443705311874215",
                "visible": true,
                "x": 295,
                "y": 355,
                "timestamp": ""
            },
            {
                "nodeID": "31_168443705311874215",
                "visible": true,
                "x": 745,
                "y": 355,
                "timestamp": "Fri May 12 2023 20:32:15 GMT+0200"
            },
            {
                "nodeID": "32_168443705311874215",
                "visible": false,
                "x": 0,
                "y": 0,
                "timestamp": ""
            },
            {
                "nodeID": "33_168443705311874215",
                "visible": false,
                "x": 0,
                "y": 0,
                "timestamp": ""
            },
            {
                "nodeID": "34_168443705311874215",
                "visible": true,
                "x": 520,
                "y": 355,
                "timestamp": ""
            },
            {
                "nodeID": "35_168443705311874215",
                "visible": true,
                "x": 282,
                "y": 422,
                "timestamp": ""
            },
            {
                "nodeID": "36_168443705311874215",
                "visible": true,
                "x": 732,
                "y": 422,
                "timestamp": "Fri May 12 2023 20:32:16 GMT+0200"
            },
            {
                "nodeID": "37_168443705311874215",
                "visible": false,
                "x": 0,
                "y": 0,
                "timestamp": ""
            },
            {
                "nodeID": "38_168443705311874215",
                "visible": false,
                "x": 0,
                "y": 0,
                "timestamp": ""
            },
            {
                "nodeID": "39_168443705311874215",
                "visible": true,
                "x": 507,
                "y": 422,
                "timestamp": ""
            },
            {
                "nodeID": "41_168443705311874215",
                "visible": true,
                "x": 291,
                "y": 516,
                "timestamp": ""
            },
            {
                "nodeID": "42_168443705311874215",
                "visible": true,
                "x": 741,
                "y": 516,
                "timestamp": "Fri May 12 2023 20:32:17 GMT+0200"
            },
            {
                "nodeID": "43_168443705311874215",
                "visible": false,
                "x": 0,
                "y": 0,
                "timestamp": ""
            },
            {
                "nodeID": "44_168443705311874215",
                "visible": false,
                "x": 0,
                "y": 0,
                "timestamp": ""
            },
            {
                "nodeID": "45_168443705311874215",
                "visible": true,
                "x": 516,
                "y": 516,
                "timestamp": ""
            },
            {
                "nodeID": "46_168443705311874215",
                "visible": true,
                "x": 891,
                "y": 385,
                "timestamp": ""
            },
            {
                "nodeID": "47_168443705311874215",
                "visible": true,
                "x": 836,
                "y": 482,
                "timestamp": ""
            },
            {
                "nodeID": "48_168443705311874215",
                "visible": true,
                "x": 309,
                "y": 603,
                "timestamp": ""
            },
            {
                "nodeID": "49_168443705311874215",
                "visible": true,
                "x": 759,
                "y": 603,
                "timestamp": "Fri May 12 2023 20:32:19 GMT+0200"
            },
            {
                "nodeID": "50_168443705311874215",
                "visible": false,
                "x": 0,
                "y": 0,
                "timestamp": ""
            },
            {
                "nodeID": "51_168443705311874215",
                "visible": false,
                "x": 0,
                "y": 0,
                "timestamp": ""
            },
            {
                "nodeID": "52_168443705311874215",
                "visible": true,
                "x": 534,
                "y": 603,
                "timestamp": ""
            },
            {
                "nodeID": "53_168443705311874215",
                "visible": true,
                "x": 881,
                "y": 557,
                "timestamp": ""
            },
            {
                "nodeID": "54_168443705311874215",
                "visible": true,
                "x": 208,
                "y": 566,
                "timestamp": ""
            },
            {
                "nodeID": "55_168443705311874215",
                "visible": true,
                "x": 530,
                "y": 560,
                "timestamp": ""
            },
            {
                "nodeID": "57_168443705311874215",
                "visible": true,
                "x": 767,
                "y": 723,
                "timestamp": "Fri May 12 2023 20:32:20 GMT+0200"
            },
            {
                "nodeID": "58_168443705311874215",
                "visible": false,
                "x": 0,
                "y": 0,
                "timestamp": ""
            },
            {
                "nodeID": "59_168443705311874215",
                "visible": false,
                "x": 0,
                "y": 0,
                "timestamp": ""
            },
            {
                "nodeID": "61_168443705311874215",
                "visible": true,
                "x": 762,
                "y": 674,
                "timestamp": ""
            },
            {
                "nodeID": "62_168443705311874215",
                "visible": true,
                "x": 535,
                "y": 653,
                "timestamp": ""
            },
            {
                "nodeID": "63_168443705311874215",
                "visible": true,
                "x": 279,
                "y": 795,
                "timestamp": ""
            },
            {
                "nodeID": "64_168443705311874215",
                "visible": true,
                "x": 754,
                "y": 799,
                "timestamp": "Fri May 12 2023 20:32:21 GMT+0200"
            },
            {
                "nodeID": "65_168443705311874215",
                "visible": false,
                "x": 0,
                "y": 0,
                "timestamp": ""
            },
            {
                "nodeID": "66_168443705311874215",
                "visible": false,
                "x": 0,
                "y": 0,
                "timestamp": ""
            },
            {
                "nodeID": "67_168443705311874215",
                "visible": true,
                "x": 529,
                "y": 799,
                "timestamp": ""
            },
            {
                "nodeID": "68_168443705311874215",
                "visible": true,
                "x": 908,
                "y": 728,
                "timestamp": ""
            },
            {
                "nodeID": "69_168443705311874215",
                "visible": true,
                "x": 268,
                "y": 729,
                "timestamp": ""
            },
            {
                "nodeID": "70_168443705311874215",
                "visible": true,
                "x": 600,
                "y": 731,
                "timestamp": ""
            },
            {
                "nodeID": "72_168443705311874215",
                "visible": true,
                "x": 759,
                "y": 892,
                "timestamp": "Fri May 12 2023 20:32:23 GMT+0200"
            },
            {
                "nodeID": "73_168443705311874215",
                "visible": false,
                "x": 0,
                "y": 0,
                "timestamp": ""
            },
            {
                "nodeID": "74_168443705311874215",
                "visible": false,
                "x": 0,
                "y": 0,
                "timestamp": ""
            },
            {
                "nodeID": "76_168443705311874215",
                "visible": true,
                "x": 747,
                "y": 849,
                "timestamp": ""
            },
            {
                "nodeID": "77_168443705311874215",
                "visible": true,
                "x": 511,
                "y": 856,
                "timestamp": ""
            },
            {
                "nodeID": "78_168443705311874215",
                "visible": true,
                "x": 286,
                "y": 957,
                "timestamp": ""
            },
            {
                "nodeID": "79_168443705311874215",
                "visible": true,
                "x": 740,
                "y": 970,
                "timestamp": "Fri May 12 2023 20:32:26 GMT+0200"
            },
            {
                "nodeID": "80_168443705311874215",
                "visible": false,
                "x": 0,
                "y": 0,
                "timestamp": ""
            },
            {
                "nodeID": "81_168443705311874215",
                "visible": false,
                "x": 0,
                "y": 0,
                "timestamp": ""
            },
            {
                "nodeID": "82_168443705311874215",
                "visible": true,
                "x": 515,
                "y": 970,
                "timestamp": ""
            },
            {
                "nodeID": "83_168443705311874215",
                "visible": true,
                "x": 903,
                "y": 937,
                "timestamp": ""
            },
            {
                "nodeID": "84_168443705311874215",
                "visible": true,
                "x": 300,
                "y": 1093,
                "timestamp": ""
            },
            {
                "nodeID": "85_168443705311874215",
                "visible": true,
                "x": 757,
                "y": 1088,
                "timestamp": "Fri May 12 2023 20:32:28 GMT+0200"
            },
            {
                "nodeID": "86_168443705311874215",
                "visible": false,
                "x": 0,
                "y": 0,
                "timestamp": ""
            },
            {
                "nodeID": "87_168443705311874215",
                "visible": false,
                "x": 0,
                "y": 0,
                "timestamp": ""
            },
            {
                "nodeID": "88_168443705311874215",
                "visible": true,
                "x": 532,
                "y": 1088,
                "timestamp": ""
            },
            {
                "nodeID": "89_168443705311874215",
                "visible": true,
                "x": 857,
                "y": 1034,
                "timestamp": ""
            },
            {
                "nodeID": "90_168443705311874215",
                "visible": true,
                "x": 294,
                "y": 1049,
                "timestamp": ""
            },
            {
                "nodeID": "91_168443705311874215",
                "visible": true,
                "x": 559,
                "y": 1047,
                "timestamp": ""
            },
            {
                "nodeID": "92_168443705311874215",
                "visible": true,
                "x": 305,
                "y": 1220,
                "timestamp": ""
            },
            {
                "nodeID": "93_168443705311874215",
                "visible": true,
                "x": 755,
                "y": 1233,
                "timestamp": "Fri May 12 2023 20:32:32 GMT+0200"
            },
            {
                "nodeID": "94_168443705311874215",
                "visible": false,
                "x": 0,
                "y": 0,
                "timestamp": ""
            },
            {
                "nodeID": "95_168443705311874215",
                "visible": false,
                "x": 0,
                "y": 0,
                "timestamp": ""
            },
            {
                "nodeID": "96_168443705311874215",
                "visible": true,
                "x": 530,
                "y": 1233,
                "timestamp": ""
            },
            {
                "nodeID": "98_168443705311874215",
                "visible": true,
                "x": 765,
                "y": 1358,
                "timestamp": "Fri May 12 2023 20:32:35 GMT+0200"
            },
            {
                "nodeID": "99_168443705311874215",
                "visible": false,
                "x": 0,
                "y": 0,
                "timestamp": ""
            },
            {
                "nodeID": "100_168443705311874215",
                "visible": false,
                "x": 0,
                "y": 0,
                "timestamp": ""
            },
            {
                "nodeID": "102_168443705311874215",
                "visible": true,
                "x": 760,
                "y": 1310,
                "timestamp": ""
            },
            {
                "nodeID": "103_168443705311874215",
                "visible": true,
                "x": 532,
                "y": 1283,
                "timestamp": ""
            },
            {
                "nodeID": "104_168443705311874215",
                "visible": true,
                "x": 304,
                "y": 1425,
                "timestamp": ""
            },
            {
                "nodeID": "105_168443705311874215",
                "visible": true,
                "x": 758,
                "y": 1428,
                "timestamp": "Fri May 12 2023 20:32:37 GMT+0200"
            },
            {
                "nodeID": "106_168443705311874215",
                "visible": false,
                "x": 0,
                "y": 0,
                "timestamp": ""
            },
            {
                "nodeID": "107_168443705311874215",
                "visible": false,
                "x": 0,
                "y": 0,
                "timestamp": ""
            },
            {
                "nodeID": "108_168443705311874215",
                "visible": true,
                "x": 507,
                "y": 1433,
                "timestamp": ""
            },
            {
                "nodeID": "112_168443705311874215",
                "visible": true,
                "x": 316,
                "y": 1553,
                "timestamp": ""
            },
            {
                "nodeID": "113_168443705311874215",
                "visible": true,
                "x": 766,
                "y": 1553,
                "timestamp": "Fri May 12 2023 20:32:40 GMT+0200"
            },
            {
                "nodeID": "114_168443705311874215",
                "visible": false,
                "x": 0,
                "y": 0,
                "timestamp": ""
            },
            {
                "nodeID": "115_168443705311874215",
                "visible": false,
                "x": 0,
                "y": 0,
                "timestamp": ""
            },
            {
                "nodeID": "116_168443705311874215",
                "visible": true,
                "x": 541,
                "y": 1553,
                "timestamp": ""
            },
            {
                "nodeID": "119_168443705311874215",
                "visible": true,
                "x": 150,
                "y": 1485,
                "timestamp": ""
            },
            {
                "nodeID": "121_168443705311874215",
                "visible": true,
                "x": 884,
                "y": 1497,
                "timestamp": ""
            },
            {
                "nodeID": "123_168443705311874215",
                "visible": true,
                "x": 555,
                "y": 1493,
                "timestamp": ""
            },
            {
                "nodeID": "125_168443705311874215",
                "visible": true,
                "x": 888,
                "y": 1665,
                "timestamp": "Fri May 12 2023 20:32:42 GMT+0200"
            },
            {
                "nodeID": "126_168443705311874215",
                "visible": false,
                "x": 0,
                "y": 0,
                "timestamp": ""
            },
            {
                "nodeID": "127_168443705311874215",
                "visible": false,
                "x": 0,
                "y": 0,
                "timestamp": ""
            },
            {
                "nodeID": "129_168443705311874215",
                "visible": true,
                "x": 777,
                "y": 1619,
                "timestamp": ""
            },
            {
                "nodeID": "130_168443705311874215",
                "visible": true,
                "x": 563,
                "y": 1609,
                "timestamp": ""
            },
            {
                "nodeID": "131_168443705311874215",
                "visible": true,
                "x": 175,
                "y": 396,
                "timestamp": ""
            },
            {
                "nodeID": "132_168443705311874215",
                "visible": true,
                "x": 532,
                "y": 393,
                "timestamp": ""
            }
        ],
        "edges": [
            {
                "fromID": "14_168443705311874215",
                "toID": "13_168443705311874215",
                "visible": false
            },
            {
                "fromID": "15_168443705311874215",
                "toID": "14_168443705311874215",
                "visible": false
            },
            {
                "fromID": "13_168443705311874215",
                "toID": "16_168443705311874215",
                "visible": true
            },
            {
                "fromID": "16_168443705311874215",
                "toID": "12_168443705311874215",
                "visible": true
            },
            {
                "fromID": "19_168443705311874215",
                "toID": "18_168443705311874215",
                "visible": false
            },
            {
                "fromID": "20_168443705311874215",
                "toID": "19_168443705311874215",
                "visible": false
            },
            {
                "fromID": "13_168443705311874215",
                "toID": "22_168443705311874215",
                "visible": true
            },
            {
                "fromID": "22_168443705311874215",
                "toID": "18_168443705311874215",
                "visible": true
            },
            {
                "fromID": "22_168443705311874215",
                "toID": "23_168443705311874215",
                "visible": true
            },
            {
                "fromID": "23_168443705311874215",
                "toID": "12_168443705311874215",
                "visible": true
            },
            {
                "fromID": "32_168443705311874215",
                "toID": "31_168443705311874215",
                "visible": false
            },
            {
                "fromID": "33_168443705311874215",
                "toID": "32_168443705311874215",
                "visible": false
            },
            {
                "fromID": "31_168443705311874215",
                "toID": "34_168443705311874215",
                "visible": true
            },
            {
                "fromID": "34_168443705311874215",
                "toID": "30_168443705311874215",
                "visible": true
            },
            {
                "fromID": "37_168443705311874215",
                "toID": "36_168443705311874215",
                "visible": false
            },
            {
                "fromID": "38_168443705311874215",
                "toID": "37_168443705311874215",
                "visible": false
            },
            {
                "fromID": "36_168443705311874215",
                "toID": "39_168443705311874215",
                "visible": true
            },
            {
                "fromID": "39_168443705311874215",
                "toID": "35_168443705311874215",
                "visible": true
            },
            {
                "fromID": "43_168443705311874215",
                "toID": "42_168443705311874215",
                "visible": false
            },
            {
                "fromID": "44_168443705311874215",
                "toID": "43_168443705311874215",
                "visible": false
            },
            {
                "fromID": "42_168443705311874215",
                "toID": "45_168443705311874215",
                "visible": true
            },
            {
                "fromID": "45_168443705311874215",
                "toID": "41_168443705311874215",
                "visible": true
            },
            {
                "fromID": "31_168443705311874215",
                "toID": "46_168443705311874215",
                "visible": true
            },
            {
                "fromID": "46_168443705311874215",
                "toID": "36_168443705311874215",
                "visible": true
            },
            {
                "fromID": "36_168443705311874215",
                "toID": "47_168443705311874215",
                "visible": true
            },
            {
                "fromID": "47_168443705311874215",
                "toID": "42_168443705311874215",
                "visible": true
            },
            {
                "fromID": "50_168443705311874215",
                "toID": "49_168443705311874215",
                "visible": false
            },
            {
                "fromID": "51_168443705311874215",
                "toID": "50_168443705311874215",
                "visible": false
            },
            {
                "fromID": "49_168443705311874215",
                "toID": "52_168443705311874215",
                "visible": true
            },
            {
                "fromID": "52_168443705311874215",
                "toID": "48_168443705311874215",
                "visible": true
            },
            {
                "fromID": "31_168443705311874215",
                "toID": "53_168443705311874215",
                "visible": true
            },
            {
                "fromID": "53_168443705311874215",
                "toID": "49_168443705311874215",
                "visible": true
            },
            {
                "fromID": "48_168443705311874215",
                "toID": "54_168443705311874215",
                "visible": true
            },
            {
                "fromID": "54_168443705311874215",
                "toID": "30_168443705311874215",
                "visible": true
            },
            {
                "fromID": "53_168443705311874215",
                "toID": "55_168443705311874215",
                "visible": true
            },
            {
                "fromID": "55_168443705311874215",
                "toID": "54_168443705311874215",
                "visible": true
            },
            {
                "fromID": "58_168443705311874215",
                "toID": "57_168443705311874215",
                "visible": false
            },
            {
                "fromID": "59_168443705311874215",
                "toID": "58_168443705311874215",
                "visible": false
            },
            {
                "fromID": "49_168443705311874215",
                "toID": "61_168443705311874215",
                "visible": true
            },
            {
                "fromID": "61_168443705311874215",
                "toID": "57_168443705311874215",
                "visible": true
            },
            {
                "fromID": "61_168443705311874215",
                "toID": "62_168443705311874215",
                "visible": true
            },
            {
                "fromID": "62_168443705311874215",
                "toID": "48_168443705311874215",
                "visible": true
            },
            {
                "fromID": "65_168443705311874215",
                "toID": "64_168443705311874215",
                "visible": false
            },
            {
                "fromID": "66_168443705311874215",
                "toID": "65_168443705311874215",
                "visible": false
            },
            {
                "fromID": "64_168443705311874215",
                "toID": "67_168443705311874215",
                "visible": true
            },
            {
                "fromID": "67_168443705311874215",
                "toID": "63_168443705311874215",
                "visible": true
            },
            {
                "fromID": "49_168443705311874215",
                "toID": "68_168443705311874215",
                "visible": true
            },
            {
                "fromID": "68_168443705311874215",
                "toID": "64_168443705311874215",
                "visible": true
            },
            {
                "fromID": "63_168443705311874215",
                "toID": "69_168443705311874215",
                "visible": true
            },
            {
                "fromID": "69_168443705311874215",
                "toID": "48_168443705311874215",
                "visible": true
            },
            {
                "fromID": "68_168443705311874215",
                "toID": "70_168443705311874215",
                "visible": true
            },
            {
                "fromID": "70_168443705311874215",
                "toID": "69_168443705311874215",
                "visible": true
            },
            {
                "fromID": "73_168443705311874215",
                "toID": "72_168443705311874215",
                "visible": false
            },
            {
                "fromID": "74_168443705311874215",
                "toID": "73_168443705311874215",
                "visible": false
            },
            {
                "fromID": "64_168443705311874215",
                "toID": "76_168443705311874215",
                "visible": true
            },
            {
                "fromID": "76_168443705311874215",
                "toID": "72_168443705311874215",
                "visible": true
            },
            {
                "fromID": "72_168443705311874215",
                "toID": "77_168443705311874215",
                "visible": true
            },
            {
                "fromID": "77_168443705311874215",
                "toID": "63_168443705311874215",
                "visible": true
            },
            {
                "fromID": "80_168443705311874215",
                "toID": "79_168443705311874215",
                "visible": false
            },
            {
                "fromID": "81_168443705311874215",
                "toID": "80_168443705311874215",
                "visible": false
            },
            {
                "fromID": "79_168443705311874215",
                "toID": "82_168443705311874215",
                "visible": true
            },
            {
                "fromID": "82_168443705311874215",
                "toID": "78_168443705311874215",
                "visible": true
            },
            {
                "fromID": "72_168443705311874215",
                "toID": "83_168443705311874215",
                "visible": true
            },
            {
                "fromID": "83_168443705311874215",
                "toID": "79_168443705311874215",
                "visible": true
            },
            {
                "fromID": "86_168443705311874215",
                "toID": "85_168443705311874215",
                "visible": false
            },
            {
                "fromID": "87_168443705311874215",
                "toID": "86_168443705311874215",
                "visible": false
            },
            {
                "fromID": "85_168443705311874215",
                "toID": "88_168443705311874215",
                "visible": true
            },
            {
                "fromID": "88_168443705311874215",
                "toID": "84_168443705311874215",
                "visible": true
            },
            {
                "fromID": "79_168443705311874215",
                "toID": "89_168443705311874215",
                "visible": true
            },
            {
                "fromID": "89_168443705311874215",
                "toID": "85_168443705311874215",
                "visible": true
            },
            {
                "fromID": "84_168443705311874215",
                "toID": "90_168443705311874215",
                "visible": true
            },
            {
                "fromID": "90_168443705311874215",
                "toID": "78_168443705311874215",
                "visible": true
            },
            {
                "fromID": "89_168443705311874215",
                "toID": "91_168443705311874215",
                "visible": true
            },
            {
                "fromID": "91_168443705311874215",
                "toID": "90_168443705311874215",
                "visible": true
            },
            {
                "fromID": "94_168443705311874215",
                "toID": "93_168443705311874215",
                "visible": false
            },
            {
                "fromID": "95_168443705311874215",
                "toID": "94_168443705311874215",
                "visible": false
            },
            {
                "fromID": "93_168443705311874215",
                "toID": "96_168443705311874215",
                "visible": true
            },
            {
                "fromID": "96_168443705311874215",
                "toID": "92_168443705311874215",
                "visible": true
            },
            {
                "fromID": "99_168443705311874215",
                "toID": "98_168443705311874215",
                "visible": false
            },
            {
                "fromID": "100_168443705311874215",
                "toID": "99_168443705311874215",
                "visible": false
            },
            {
                "fromID": "93_168443705311874215",
                "toID": "102_168443705311874215",
                "visible": true
            },
            {
                "fromID": "102_168443705311874215",
                "toID": "98_168443705311874215",
                "visible": true
            },
            {
                "fromID": "102_168443705311874215",
                "toID": "103_168443705311874215",
                "visible": true
            },
            {
                "fromID": "103_168443705311874215",
                "toID": "92_168443705311874215",
                "visible": true
            },
            {
                "fromID": "106_168443705311874215",
                "toID": "105_168443705311874215",
                "visible": false
            },
            {
                "fromID": "107_168443705311874215",
                "toID": "106_168443705311874215",
                "visible": false
            },
            {
                "fromID": "105_168443705311874215",
                "toID": "108_168443705311874215",
                "visible": true
            },
            {
                "fromID": "108_168443705311874215",
                "toID": "104_168443705311874215",
                "visible": true
            },
            {
                "fromID": "114_168443705311874215",
                "toID": "113_168443705311874215",
                "visible": false
            },
            {
                "fromID": "115_168443705311874215",
                "toID": "114_168443705311874215",
                "visible": false
            },
            {
                "fromID": "113_168443705311874215",
                "toID": "116_168443705311874215",
                "visible": true
            },
            {
                "fromID": "116_168443705311874215",
                "toID": "112_168443705311874215",
                "visible": true
            },
            {
                "fromID": "92_168443705311874215",
                "toID": "119_168443705311874215",
                "visible": true
            },
            {
                "fromID": "119_168443705311874215",
                "toID": "112_168443705311874215",
                "visible": true
            },
            {
                "fromID": "104_168443705311874215",
                "toID": "119_168443705311874215",
                "visible": true
            },
            {
                "fromID": "105_168443705311874215",
                "toID": "121_168443705311874215",
                "visible": true
            },
            {
                "fromID": "121_168443705311874215",
                "toID": "113_168443705311874215",
                "visible": true
            },
            {
                "fromID": "93_168443705311874215",
                "toID": "121_168443705311874215",
                "visible": true
            },
            {
                "fromID": "121_168443705311874215",
                "toID": "123_168443705311874215",
                "visible": true
            },
            {
                "fromID": "123_168443705311874215",
                "toID": "119_168443705311874215",
                "visible": true
            },
            {
                "fromID": "126_168443705311874215",
                "toID": "125_168443705311874215",
                "visible": false
            },
            {
                "fromID": "127_168443705311874215",
                "toID": "126_168443705311874215",
                "visible": false
            },
            {
                "fromID": "113_168443705311874215",
                "toID": "129_168443705311874215",
                "visible": true
            },
            {
                "fromID": "129_168443705311874215",
                "toID": "125_168443705311874215",
                "visible": true
            },
            {
                "fromID": "129_168443705311874215",
                "toID": "130_168443705311874215",
                "visible": true
            },
            {
                "fromID": "130_168443705311874215",
                "toID": "112_168443705311874215",
                "visible": true
            },
            {
                "fromID": "35_168443705311874215",
                "toID": "131_168443705311874215",
                "visible": true
            },
            {
                "fromID": "131_168443705311874215",
                "toID": "30_168443705311874215",
                "visible": true
            },
            {
                "fromID": "46_168443705311874215",
                "toID": "132_168443705311874215",
                "visible": true
            },
            {
                "fromID": "132_168443705311874215",
                "toID": "131_168443705311874215",
                "visible": true
            }
        ]
    }
}